utils/__init__.py
utils/api.py
utils/auth.py
utils/generic.py
utils/io.py
utils/jupyterlite.py
utils/material.py
utils/notebook.py
utils/plot.py
utils/settings.json
utils/settings.py
utils/visualize.py
utils/web/renderjson.css
utils/web/renderjson.js
mat3ra_api_examples-2026.1.23.post0.dist-info/METADATA
mat3ra_api_examples-2026.1.23.post0.dist-info/WHEEL
mat3ra_api_examples-2026.1.23.post0.dist-info/entry_points.txt
mat3ra_api_examples-2026.1.23.post0.dist-info/top_level.txt
mat3ra_api_examples-2026.1.23.post0.dist-info/RECORD
