Metadata-Version: 2.4
Name: mat3ra-api-examples
Version: 2026.1.23.post0
Summary: Mat3ra API Examples
Project-URL: homepage, https://exabyte-io.github.io/api-examples
Project-URL: documentation, https://exabyte-io.github.io/api-examples
Project-URL: repository, https://github.com/Exabyte-io/api-examples
Requires-Python: >=3.10
Requires-Dist: ase>=3.25.0
Requires-Dist: mat3ra-api-client>=2026.1.23.post0
Requires-Dist: matplotlib>=3.4.1
Requires-Dist: pandas>=1.5.3
Requires-Dist: pymatgen==2024.4.13
Requires-Dist: mat3ra-made>=2025.8.13.post0
Requires-Dist: mat3ra-utils>=2024.6.11.post0
Requires-Dist: mat3ra-wode
Provides-Extra: colab
Requires-Dist: mat3ra-api-examples; extra == "colab"
Provides-Extra: jupyterlab
Requires-Dist: jupyterlab>=3.0.17; extra == "jupyterlab"
Requires-Dist: nbconvert>=6.0.7; extra == "jupyterlab"
Provides-Extra: localhost
Requires-Dist: mat3ra-api-examples[jupyterlab]; extra == "localhost"
Provides-Extra: dev
Requires-Dist: pre-commit>=3.3.3; extra == "dev"
Requires-Dist: pip-tools>=6.13.0; extra == "dev"
Provides-Extra: docs
Requires-Dist: mkdocs>=1.4.3; extra == "docs"
Requires-Dist: mkdocs-material>=9.1.17; extra == "docs"
Requires-Dist: mkdocs-same-dir>=0.1.2; extra == "docs"
Requires-Dist: mkdocs-exclude>=1.0.2; extra == "docs"
Requires-Dist: mkdocs-jupyter>=0.24.1; extra == "docs"
Requires-Dist: nbstripout>=0.6.1; extra == "docs"
Provides-Extra: forcefields
Requires-Dist: mattersim>=1.2.0; extra == "forcefields"
